STT_Module/__init__.py
STT_Module-1.0.dist-info/METADATA
STT_Module-1.0.dist-info/WHEEL
STT_Module-1.0.dist-info/top_level.txt
STT_Module-1.0.dist-info/RECORD
